picosvg/__init__.py
picosvg/_version.py
picosvg/arc_to_cubic.py
picosvg/geometric_types.py
picosvg/picosvg.py
picosvg/py.typed
picosvg/svg.py
picosvg/svg_meta.py
picosvg/svg_path_iter.py
picosvg/svg_pathops.py
picosvg/svg_reuse.py
picosvg/svg_transform.py
picosvg/svg_types.py
picosvg-0.22.1.dist-info/LICENSE
picosvg-0.22.1.dist-info/METADATA
picosvg-0.22.1.dist-info/WHEEL
picosvg-0.22.1.dist-info/entry_points.txt
picosvg-0.22.1.dist-info/top_level.txt
picosvg-0.22.1.dist-info/RECORD
