Metadata-Version: 2.1
Name: picosvg
Version: 0.22.1
Summary: Exploratory utility for svg simplification, meant for use playing with COLR fonts
Author: Rod S
Author-email: rsheeter@google.com
Requires-Python: >=3.8
Provides-Extra: dev
License-File: LICENSE
